Metadata-Version: 2.1
Name: box-bsxpath
Version: 0.1.3
Summary: BS emulate
Home-page: UNKNOWN
Author: Arturas Adamonis
Author-email: artplus447@gmail.com
License: UNKNOWN
Platform: UNKNOWN
